tsubame/__init__.py
tsubame/traceroute.py
tsubame-0.8.2.dist-info/LICENSE
tsubame-0.8.2.dist-info/METADATA
tsubame-0.8.2.dist-info/WHEEL
tsubame-0.8.2.dist-info/entry_points.txt
tsubame-0.8.2.dist-info/top_level.txt
tsubame-0.8.2.dist-info/RECORD
