Metadata-Version: 2.1
Name: tsubame
Version: 0.8.2
Summary: Quick Traceroute
Home-page: https://github.com/nbtk/tsubame
Author: nbtk
License: BSD
Classifier: Development Status :: 3 - Alpha
Classifier: Programming Language :: Python :: 3
Classifier: License :: OSI Approved :: BSD License
Requires-Python: >=3.7
License-File: LICENSE
